dingtalk_crypto/__init__.py
dingtalk_crypto/crypto.py
dingtalk_crypto/pkcs7.py
dingtalk_crypto/utils.py
dingtalk_crypto-1.0.2.dist-info/DESCRIPTION.rst
dingtalk_crypto-1.0.2.dist-info/METADATA
dingtalk_crypto-1.0.2.dist-info/RECORD
dingtalk_crypto-1.0.2.dist-info/WHEEL
dingtalk_crypto-1.0.2.dist-info/metadata.json
dingtalk_crypto-1.0.2.dist-info/top_level.txt
tests/__init__.py
tests/test_crypto.py
