Metadata-Version: 2.0
Name: dingtalk-crypto
Version: 1.0.2
Summary: 钉钉加密解密工具
Home-page: https://github.com/zgs225/dingtalk_crypto
Author: Yuez
Author-email: i@yuez.me
License: MIT
Platform: UNKNOWN
Classifier: Development Status :: 5 - Production/Stable
Classifier: Intended Audience :: Developers
Classifier: Programming Language :: Python
Classifier: Programming Language :: Python :: 2.6
Classifier: Programming Language :: Python :: 2.7
Classifier: Programming Language :: Python :: 3
Classifier: Programming Language :: Python :: 3.3
Classifier: Programming Language :: Python :: 3.4
Classifier: Programming Language :: Python :: 3.5
Requires-Dist: pycrypto
